<annotationInfo>
<annotationInfo>
<item  id="32" filename="src/snake_output.cpp" linenumber="28" name="p_shl" contextFuncName="snake_output" moduleName="snake_output" rtlName="p_shl_fu_373_p3" latency="0" BRAM="-1" DSP="-1" FF="-1" LUT="-1" fileDirectory="C:\Users\shinderink\REC\snake_output"><\/item>
<item  id="33" filename="src/snake_output.cpp" linenumber="28" name="p_shl2" contextFuncName="snake_output" moduleName="snake_output" rtlName="p_shl2_fu_381_p3" latency="0" BRAM="-1" DSP="-1" FF="-1" LUT="-1" fileDirectory="C:\Users\shinderink\REC\snake_output"><\/item>
<item  id="34" filename="src/snake_output.cpp" linenumber="28" name="p_shl2_cast" contextFuncName="snake_output" moduleName="snake_output" rtlName="p_shl2_cast_fu_389_p1" latency="0" BRAM="-1" DSP="-1" FF="-1" LUT="-1" fileDirectory="C:\Users\shinderink\REC\snake_output"><\/item>
<item  id="35" filename="src/snake_output.cpp" linenumber="28" name="ret_V" contextFuncName="snake_output" moduleName="snake_output" rtlName="ret_V_fu_393_p2" latency="0" BRAM="-1" DSP="-1" FF="0" LUT="15" fileDirectory="C:\Users\shinderink\REC\snake_output"><\/item>
<item  id="36" filename="src/snake_output.cpp" linenumber="55" name="tmp_8" contextFuncName="snake_output" moduleName="snake_output" rtlName="tmp_8_fu_589_p3" latency="0" BRAM="-1" DSP="-1" FF="-1" LUT="-1" fileDirectory="C:\Users\shinderink\REC\snake_output"><\/item>
<item  id="37" filename="src/snake_output.cpp" linenumber="55" name="zext_cast" contextFuncName="snake_output" moduleName="snake_output" rtlName="mul_fu_1462_p00" latency="0" BRAM="-1" DSP="-1" FF="-1" LUT="-1" fileDirectory="C:\Users\shinderink\REC\snake_output"><\/item>
<item  id="38" filename="src/snake_output.cpp" linenumber="55" name="mul" contextFuncName="snake_output" moduleName="snake_output" rtlName="snake_output_mul_g8j_U10" latency="0" BRAM="-1" DSP="-1" FF="-1" LUT="-1" fileDirectory="C:\Users\shinderink\REC\snake_output"><\/item>
<item  id="44" filename="src/snake_output.cpp" linenumber="14" name="frame_V" contextFuncName="snake_output" moduleName="snake_output" rtlName="frame_V_fu_411_p2" latency="0" BRAM="-1" DSP="-1" FF="0" LUT="15" fileDirectory="C:\Users\shinderink\REC\snake_output"><\/item>
<item  id="47" filename="src/snake_output.cpp" linenumber="16" name="t_V_1_mid" contextFuncName="snake_output" moduleName="snake_output" rtlName="t_V_1_mid_fu_423_p3" latency="0" BRAM="-1" DSP="-1" FF="0" LUT="10" fileDirectory="C:\Users\shinderink\REC\snake_output"><\/item>
<item  id="48" filename="src/snake_output.cpp" linenumber="28" name="p_shl_mid1" contextFuncName="snake_output" moduleName="snake_output" rtlName="p_shl_mid1_fu_431_p3" latency="0" BRAM="-1" DSP="-1" FF="-1" LUT="-1" fileDirectory="C:\Users\shinderink\REC\snake_output"><\/item>
<item  id="49" filename="src/snake_output.cpp" linenumber="28" name="p_shl2_mid1" contextFuncName="snake_output" moduleName="snake_output" rtlName="p_shl2_mid1_fu_439_p3" latency="0" BRAM="-1" DSP="-1" FF="-1" LUT="-1" fileDirectory="C:\Users\shinderink\REC\snake_output"><\/item>
<item  id="50" filename="src/snake_output.cpp" linenumber="28" name="p_shl2_cast_mid1" contextFuncName="snake_output" moduleName="snake_output" rtlName="p_shl2_cast_mid1_fu_447_p1" latency="0" BRAM="-1" DSP="-1" FF="-1" LUT="-1" fileDirectory="C:\Users\shinderink\REC\snake_output"><\/item>
<item  id="51" filename="src/snake_output.cpp" linenumber="28" name="ret_V_mid1" contextFuncName="snake_output" moduleName="snake_output" rtlName="ret_V_mid1_fu_451_p2" latency="0" BRAM="-1" DSP="-1" FF="0" LUT="15" fileDirectory="C:\Users\shinderink\REC\snake_output"><\/item>
<item  id="52" filename="src/snake_output.cpp" linenumber="32" name="x_assign_mid2_v_v_v" contextFuncName="snake_output" moduleName="snake_output" rtlName="x_assign_mid2_v_v_v_fu_457_p3" latency="0" BRAM="-1" DSP="-1" FF="0" LUT="9" fileDirectory="C:\Users\shinderink\REC\snake_output"><\/item>
<item  id="53" filename="src/snake_output.cpp" linenumber="32" name="x_assign_mid2_v_v" contextFuncName="snake_output" moduleName="snake_output" rtlName="grp_fu_367_p0" latency="0" BRAM="-1" DSP="-1" FF="-1" LUT="-1" fileDirectory="C:\Users\shinderink\REC\snake_output"><\/item>
<item  id="54" filename="src/snake_output.cpp" linenumber="32" name="x_assign_mid2_v" contextFuncName="snake_output" moduleName="snake_output" rtlName="snake_output_sitoeOg_U8" latency="5" BRAM="-1" DSP="-1" FF="-1" LUT="-1" fileDirectory="C:\Users\shinderink\REC\snake_output"><\/item>
<item  id="55" filename="src/snake_output.cpp" linenumber="32" name="x_assign_mid2" contextFuncName="snake_output" moduleName="snake_output" rtlName="snake_output_ddivdEe_U7" latency="30" BRAM="-1" DSP="-1" FF="-1" LUT="-1" fileDirectory="C:\Users\shinderink\REC\snake_output"><\/item>
<item  id="56" filename="r:/builds/2018.3/continuous/2018_12_06_2405991/src/products/hls/hls_lib/src/hls\utils/x_hls_utils.h" linenumber="475" name="val_assign_mid2" contextFuncName="fp_struct" moduleName="snake_output" rtlName="val_assign_mid2_fu_677_p1" latency="0" BRAM="-1" DSP="-1" FF="-1" LUT="-1" fileDirectory="r:\builds\2018.3\continuous\2018_12_06_2405991\src\products"><\/item>
<item  id="57" filename="r:/builds/2018.3/continuous/2018_12_06_2405991/src/products/hls/hls_lib/src/hls\utils/x_hls_utils.h" linenumber="475" name="tmp_1" contextFuncName="fp_struct" moduleName="snake_output" rtlName="tmp_1_reg_1603" latency="0" BRAM="-1" DSP="-1" FF="-1" LUT="-1" fileDirectory="r:\builds\2018.3\continuous\2018_12_06_2405991\src\products"><\/item>
<item  id="58" filename="src/snake_output.cpp" linenumber="16" name="not_exitcond_flatten" contextFuncName="snake_output" moduleName="snake_output" rtlName="not_exitcond_flatten_fu_465_p2" latency="0" BRAM="-1" DSP="-1" FF="0" LUT="2" fileDirectory="C:\Users\shinderink\REC\snake_output"><\/item>
<item  id="59" filename="src/snake_output.cpp" linenumber="16" name="tmp_3" contextFuncName="snake_output" moduleName="snake_output" rtlName="tmp_3_fu_471_p2" latency="0" BRAM="-1" DSP="-1" FF="0" LUT="13" fileDirectory="C:\Users\shinderink\REC\snake_output"><\/item>
<item  id="60" filename="src/snake_output.cpp" linenumber="16" name="tmp_1_mid" contextFuncName="snake_output" moduleName="snake_output" rtlName="tmp_1_mid_fu_477_p2" latency="0" BRAM="-1" DSP="-1" FF="0" LUT="2" fileDirectory="C:\Users\shinderink\REC\snake_output"><\/item>
<item  id="61" filename="src/snake_output.cpp" linenumber="14" name="t_V_mid2" contextFuncName="snake_output" moduleName="snake_output" rtlName="t_V_mid2_fu_483_p3" latency="0" BRAM="-1" DSP="-1" FF="0" LUT="6" fileDirectory="C:\Users\shinderink\REC\snake_output"><\/item>
<item  id="62" filename="src/snake_output.cpp" linenumber="15" name="row_V" contextFuncName="snake_output" moduleName="snake_output" rtlName="row_V_fu_491_p2" latency="0" BRAM="-1" DSP="-1" FF="0" LUT="14" fileDirectory="C:\Users\shinderink\REC\snake_output"><\/item>
<item  id="64" filename="src/snake_output.cpp" linenumber="16" name="tmp" contextFuncName="snake_output" moduleName="snake_output" rtlName="tmp_fu_497_p2" latency="0" BRAM="-1" DSP="-1" FF="0" LUT="2" fileDirectory="C:\Users\shinderink\REC\snake_output"><\/item>
<item  id="65" filename="src/snake_output.cpp" linenumber="16" name="t_V_2_mid2" contextFuncName="snake_output" moduleName="snake_output" rtlName="t_V_2_mid2_fu_503_p3" latency="0" BRAM="-1" DSP="-1" FF="0" LUT="10" fileDirectory="C:\Users\shinderink\REC\snake_output"><\/item>
<item  id="66" filename="src/snake_output.cpp" linenumber="55" name="tmp_8_mid1" contextFuncName="snake_output" moduleName="snake_output" rtlName="tmp_8_mid1_fu_605_p3" latency="0" BRAM="-1" DSP="-1" FF="-1" LUT="-1" fileDirectory="C:\Users\shinderink\REC\snake_output"><\/item>
<item  id="67" filename="src/snake_output.cpp" linenumber="55" name="zext1_cast" contextFuncName="snake_output" moduleName="snake_output" rtlName="mul2_fu_1468_p00" latency="0" BRAM="-1" DSP="-1" FF="-1" LUT="-1" fileDirectory="C:\Users\shinderink\REC\snake_output"><\/item>
<item  id="68" filename="src/snake_output.cpp" linenumber="55" name="mul2" contextFuncName="snake_output" moduleName="snake_output" rtlName="snake_output_mul_g8j_U11" latency="0" BRAM="-1" DSP="-1" FF="-1" LUT="-1" fileDirectory="C:\Users\shinderink\REC\snake_output"><\/item>
<item  id="69" filename="src/snake_output.cpp" linenumber="55" name="tmp_4" contextFuncName="snake_output" moduleName="snake_output" rtlName="tmp_4_fu_628_p4" latency="0" BRAM="-1" DSP="-1" FF="-1" LUT="-1" fileDirectory="C:\Users\shinderink\REC\snake_output"><\/item>
<item  id="70" filename="src/snake_output.cpp" linenumber="55" name="tmp_5" contextFuncName="snake_output" moduleName="snake_output" rtlName="tmp_5_fu_637_p4" latency="0" BRAM="-1" DSP="-1" FF="-1" LUT="-1" fileDirectory="C:\Users\shinderink\REC\snake_output"><\/item>
<item  id="71" filename="src/snake_output.cpp" linenumber="58" name="tmp_11" contextFuncName="snake_output" moduleName="snake_output" rtlName="tmp_11_fu_646_p3" latency="0" BRAM="-1" DSP="-1" FF="0" LUT="6" fileDirectory="C:\Users\shinderink\REC\snake_output"><\/item>
<item  id="72" filename="src/snake_output.cpp" linenumber="58" name="tmp_12" contextFuncName="snake_output" moduleName="snake_output" rtlName="tmp_12_fu_653_p3" latency="0" BRAM="-1" DSP="-1" FF="0" LUT="6" fileDirectory="C:\Users\shinderink\REC\snake_output"><\/item>
<item  id="73" filename="src/snake_output.cpp" linenumber="58" name="tmp_21_cast" contextFuncName="snake_output" moduleName="snake_output" rtlName="tmp_21_cast_fu_660_p3" latency="0" BRAM="-1" DSP="-1" FF="-1" LUT="-1" fileDirectory="C:\Users\shinderink\REC\snake_output"><\/item>
<item  id="74" filename="src/snake_output.cpp" linenumber="16" name="t_V_1_mid2" contextFuncName="snake_output" moduleName="snake_output" rtlName="t_V_1_mid2_fu_511_p3" latency="0" BRAM="-1" DSP="-1" FF="0" LUT="10" fileDirectory="C:\Users\shinderink\REC\snake_output"><\/item>
<item  id="78" filename="src/snake_output.cpp" linenumber="20" name="tmp_2" contextFuncName="snake_output" moduleName="snake_output" rtlName="tmp_2_fu_519_p2" latency="0" BRAM="-1" DSP="-1" FF="0" LUT="10" fileDirectory="C:\Users\shinderink\REC\snake_output"><\/item>
<item  id="79" filename="src/snake_output.cpp" linenumber="20" name="tmp_user_V" contextFuncName="snake_output" moduleName="snake_output" rtlName="tmp_user_V_fu_525_p2" latency="0" BRAM="-1" DSP="-1" FF="0" LUT="13" fileDirectory="C:\Users\shinderink\REC\snake_output"><\/item>
<item  id="80" filename="src/snake_output.cpp" linenumber="23" name="tmp_last_V" contextFuncName="snake_output" moduleName="snake_output" rtlName="tmp_last_V_fu_531_p2" latency="0" BRAM="-1" DSP="-1" FF="0" LUT="13" fileDirectory="C:\Users\shinderink\REC\snake_output"><\/item>
<item  id="81" filename="src/snake_output.cpp" linenumber="26" name="tmp_6" contextFuncName="snake_output" moduleName="snake_output" rtlName="tmp_6_fu_537_p2" latency="0" BRAM="-1" DSP="-1" FF="0" LUT="13" fileDirectory="C:\Users\shinderink\REC\snake_output"><\/item>
<item  id="82" filename="src/snake_output.cpp" linenumber="26" name="tmp_9" contextFuncName="snake_output" moduleName="snake_output" rtlName="tmp_9_fu_543_p2" latency="0" BRAM="-1" DSP="-1" FF="0" LUT="13" fileDirectory="C:\Users\shinderink\REC\snake_output"><\/item>
<item  id="83" filename="src/snake_output.cpp" linenumber="26" name="or_cond" contextFuncName="snake_output" moduleName="snake_output" rtlName="or_cond_fu_549_p2" latency="0" BRAM="-1" DSP="-1" FF="0" LUT="2" fileDirectory="C:\Users\shinderink\REC\snake_output"><\/item>
<item  id="86" filename="src/snake_output.cpp" linenumber="56" name="ret_V_1" contextFuncName="snake_output" moduleName="snake_output" rtlName="ret_V_1_fu_555_p3" latency="0" BRAM="-1" DSP="-1" FF="-1" LUT="-1" fileDirectory="C:\Users\shinderink\REC\snake_output"><\/item>
<item  id="87" filename="src/snake_output.cpp" linenumber="56" name="ret_V_2" contextFuncName="snake_output" moduleName="snake_output" rtlName="ret_V_2_fu_563_p2" latency="0" BRAM="-1" DSP="-1" FF="0" LUT="19" fileDirectory="C:\Users\shinderink\REC\snake_output"><\/item>
<item  id="88" filename="src/snake_output.cpp" linenumber="56" name="zext3_cast" contextFuncName="snake_output" moduleName="snake_output" rtlName="mul4_fu_1474_p00" latency="0" BRAM="-1" DSP="-1" FF="-1" LUT="-1" fileDirectory="C:\Users\shinderink\REC\snake_output"><\/item>
<item  id="89" filename="src/snake_output.cpp" linenumber="56" name="mul4" contextFuncName="snake_output" moduleName="snake_output" rtlName="snake_output_mul_g8j_U12" latency="0" BRAM="-1" DSP="-1" FF="-1" LUT="-1" fileDirectory="C:\Users\shinderink\REC\snake_output"><\/item>
<item  id="90" filename="src/snake_output.cpp" linenumber="58" name="tmp_34" contextFuncName="snake_output" moduleName="snake_output" rtlName="tmp_34_reg_1582" latency="0" BRAM="-1" DSP="-1" FF="-1" LUT="-1" fileDirectory="C:\Users\shinderink\REC\snake_output"><\/item>
<item  id="91" filename="src/snake_output.cpp" linenumber="58" name="tmp_12_cast" contextFuncName="snake_output" moduleName="snake_output" rtlName="tmp_12_cast_fu_668_p1" latency="0" BRAM="-1" DSP="-1" FF="-1" LUT="-1" fileDirectory="C:\Users\shinderink\REC\snake_output"><\/item>
<item  id="92" filename="src/snake_output.cpp" linenumber="58" name="tmp_31" contextFuncName="snake_output" moduleName="snake_output" rtlName="tmp_31_fu_671_p2" latency="0" BRAM="-1" DSP="-1" FF="0" LUT="14" fileDirectory="C:\Users\shinderink\REC\snake_output"><\/item>
<item  id="93" filename="src/snake_output.cpp" linenumber="58" name="tmp_41_cast" contextFuncName="snake_output" moduleName="snake_output" rtlName="tmp_41_cast_fu_992_p1" latency="0" BRAM="-1" DSP="-1" FF="-1" LUT="-1" fileDirectory="C:\Users\shinderink\REC\snake_output"><\/item>
<item  id="96" filename="src/snake_output.cpp" linenumber="58" name="tmp_35" contextFuncName="snake_output" moduleName="snake_output" rtlName="tmp_35_fu_1383_p3" latency="0" BRAM="-1" DSP="-1" FF="-1" LUT="-1" fileDirectory="C:\Users\shinderink\REC\snake_output"><\/item>
<item  id="99" filename="src/snake_output.cpp" linenumber="62" name="tmp_14" contextFuncName="snake_output" moduleName="snake_output" rtlName="tmp_14_fu_1391_p2" latency="0" BRAM="-1" DSP="-1" FF="0" LUT="18" fileDirectory="C:\Users\shinderink\REC\snake_output"><\/item>
<item  id="100" filename="src/snake_output.cpp" linenumber="62" name="G_cast_cast" contextFuncName="snake_output" moduleName="snake_output" rtlName="G_cast_cast_fu_1397_p3" latency="0" BRAM="-1" DSP="-1" FF="0" LUT="8" fileDirectory="C:\Users\shinderink\REC\snake_output"><\/item>
<item  id="106" filename="r:/builds/2018.3/continuous/2018_12_06_2405991/src/products/hls/hls_lib/src/hls\utils/x_hls_utils.h" linenumber="477" name="tmp_V" contextFuncName="fp_struct" moduleName="snake_output" rtlName="tmp_V_fu_688_p4" latency="0" BRAM="-1" DSP="-1" FF="-1" LUT="-1" fileDirectory="r:\builds\2018.3\continuous\2018_12_06_2405991\src\products"><\/item>
<item  id="107" filename="r:/builds/2018.3/continuous/2018_12_06_2405991/src/products/hls/hls_lib/src/hls\utils/x_hls_utils.h" linenumber="478" name="tmp_V_1" contextFuncName="fp_struct" moduleName="snake_output" rtlName="tmp_V_1_fu_698_p1" latency="0" BRAM="-1" DSP="-1" FF="-1" LUT="-1" fileDirectory="r:\builds\2018.3\continuous\2018_12_06_2405991\src\products"><\/item>
<item  id="108" filename="r:/builds/2018.3/continuous/2018_12_06_2405991/src/products/hls/hls_lib/hlsmath/include/FloatingPoint\hls_case_IEEE754.h" linenumber="14" name="mantissa_V" contextFuncName="generic_cast_IEEE754&lt;int, 6, double&gt;" moduleName="snake_output" rtlName="mantissa_V_fu_702_p4" latency="0" BRAM="-1" DSP="-1" FF="-1" LUT="-1" fileDirectory="r:\builds\2018.3\continuous\2018_12_06_2405991\src\products"><\/item>
<item  id="109" filename="r:/builds/2018.3/continuous/2018_12_06_2405991/src/products/hls/hls_lib/hlsmath/include/FloatingPoint\hls_case_IEEE754.h" linenumber="14" name="mantissa_V_1_cast" contextFuncName="generic_cast_IEEE754&lt;int, 6, double&gt;" moduleName="snake_output" rtlName="mantissa_V_1_cast_fu_712_p1" latency="0" BRAM="-1" DSP="-1" FF="-1" LUT="-1" fileDirectory="r:\builds\2018.3\continuous\2018_12_06_2405991\src\products"><\/item>
<item  id="110" filename="r:/builds/2018.3/continuous/2018_12_06_2405991/src/products/hls/hls_lib/src/hls\utils/x_hls_utils.h" linenumber="502" name="tmp_i_i_i_i_cast" contextFuncName="expv" moduleName="snake_output" rtlName="tmp_i_i_i_i_cast_fu_716_p1" latency="0" BRAM="-1" DSP="-1" FF="-1" LUT="-1" fileDirectory="r:\builds\2018.3\continuous\2018_12_06_2405991\src\products"><\/item>
<item  id="111" filename="r:/builds/2018.3/continuous/2018_12_06_2405991/src/products/hls/hls_lib/src/hls\utils/x_hls_utils.h" linenumber="502" name="sh_assign" contextFuncName="expv" moduleName="snake_output" rtlName="sh_assign_fu_720_p2" latency="0" BRAM="-1" DSP="-1" FF="0" LUT="12" fileDirectory="r:\builds\2018.3\continuous\2018_12_06_2405991\src\products"><\/item>
<item  id="112" filename="r:/builds/2018.3/continuous/2018_12_06_2405991/src/products/hls/hls_lib/hlsmath/include/FloatingPoint\hls_case_IEEE754.h" linenumber="17" name="isNeg" contextFuncName="generic_cast_IEEE754&lt;int, 6, double&gt;" moduleName="snake_output" rtlName="isNeg_fu_726_p3" latency="0" BRAM="-1" DSP="-1" FF="-1" LUT="-1" fileDirectory="r:\builds\2018.3\continuous\2018_12_06_2405991\src\products"><\/item>
<item  id="113" filename="r:/builds/2018.3/continuous/2018_12_06_2405991/src/products/hls/hls_lib/hlsmath/include/FloatingPoint\hls_case_IEEE754.h" linenumber="17" name="tmp_i_i_i" contextFuncName="generic_cast_IEEE754&lt;int, 6, double&gt;" moduleName="snake_output" rtlName="tmp_i_i_i_fu_734_p2" latency="0" BRAM="-1" DSP="-1" FF="0" LUT="13" fileDirectory="r:\builds\2018.3\continuous\2018_12_06_2405991\src\products"><\/item>
<item  id="114" filename="r:/builds/2018.3/continuous/2018_12_06_2405991/src/products/hls/hls_lib/hlsmath/include/FloatingPoint\hls_case_IEEE754.h" linenumber="17" name="tmp_i_i_i_cast" contextFuncName="generic_cast_IEEE754&lt;int, 6, double&gt;" moduleName="snake_output" rtlName="tmp_i_i_i_cast_fu_740_p1" latency="0" BRAM="-1" DSP="-1" FF="-1" LUT="-1" fileDirectory="r:\builds\2018.3\continuous\2018_12_06_2405991\src\products"><\/item>
<item  id="115" filename="r:/builds/2018.3/continuous/2018_12_06_2405991/src/products/hls/hls_lib/hlsmath/include/FloatingPoint\hls_case_IEEE754.h" linenumber="17" name="ush" contextFuncName="generic_cast_IEEE754&lt;int, 6, double&gt;" moduleName="snake_output" rtlName="ush_fu_744_p3" latency="0" BRAM="-1" DSP="-1" FF="0" LUT="12" fileDirectory="r:\builds\2018.3\continuous\2018_12_06_2405991\src\products"><\/item>
<item  id="116" filename="r:/builds/2018.3/continuous/2018_12_06_2405991/src/products/hls/hls_lib/hlsmath/include/FloatingPoint\hls_case_IEEE754.h" linenumber="17" name="sh_assign_2_cast" contextFuncName="generic_cast_IEEE754&lt;int, 6, double&gt;" moduleName="snake_output" rtlName="sh_assign_2_cast_fu_752_p1" latency="0" BRAM="-1" DSP="-1" FF="-1" LUT="-1" fileDirectory="r:\builds\2018.3\continuous\2018_12_06_2405991\src\products"><\/item>
<item  id="117" filename="r:/builds/2018.3/continuous/2018_12_06_2405991/src/products/hls/hls_lib/hlsmath/include/FloatingPoint\hls_case_IEEE754.h" linenumber="17" name="tmp_i_i_i_9" contextFuncName="generic_cast_IEEE754&lt;int, 6, double&gt;" moduleName="snake_output" rtlName="tmp_i_i_i_9_fu_756_p1" latency="0" BRAM="-1" DSP="-1" FF="-1" LUT="-1" fileDirectory="r:\builds\2018.3\continuous\2018_12_06_2405991\src\products"><\/item>
<item  id="118" filename="r:/builds/2018.3/continuous/2018_12_06_2405991/src/products/hls/hls_lib/hlsmath/include/FloatingPoint\hls_case_IEEE754.h" linenumber="17" name="tmp_i_i_i_cast_10" contextFuncName="generic_cast_IEEE754&lt;int, 6, double&gt;" moduleName="snake_output" rtlName="tmp_i_i_i_cast_10_fu_760_p1" latency="0" BRAM="-1" DSP="-1" FF="-1" LUT="-1" fileDirectory="r:\builds\2018.3\continuous\2018_12_06_2405991\src\products"><\/item>
<item  id="119" filename="r:/builds/2018.3/continuous/2018_12_06_2405991/src/products/hls/hls_lib/hlsmath/include/FloatingPoint\hls_case_IEEE754.h" linenumber="17" name="r_V" contextFuncName="generic_cast_IEEE754&lt;int, 6, double&gt;" moduleName="snake_output" rtlName="r_V_fu_764_p2" latency="0" BRAM="-1" DSP="-1" FF="0" LUT="162" fileDirectory="r:\builds\2018.3\continuous\2018_12_06_2405991\src\products"><\/item>
<item  id="120" filename="r:/builds/2018.3/continuous/2018_12_06_2405991/src/products/hls/hls_lib/hlsmath/include/FloatingPoint\hls_case_IEEE754.h" linenumber="17" name="r_V_1" contextFuncName="generic_cast_IEEE754&lt;int, 6, double&gt;" moduleName="snake_output" rtlName="r_V_1_fu_770_p2" latency="0" BRAM="-1" DSP="-1" FF="0" LUT="474" fileDirectory="r:\builds\2018.3\continuous\2018_12_06_2405991\src\products"><\/item>
<item  id="121" filename="r:/builds/2018.3/continuous/2018_12_06_2405991/src/products/hls/hls_lib/hlsmath/include/FloatingPoint\hls_case_IEEE754.h" linenumber="20" name="tmp_16" contextFuncName="generic_cast_IEEE754&lt;int, 6, double&gt;" moduleName="snake_output" rtlName="tmp_16_fu_776_p3" latency="0" BRAM="-1" DSP="-1" FF="-1" LUT="-1" fileDirectory="r:\builds\2018.3\continuous\2018_12_06_2405991\src\products"><\/item>
<item  id="122" filename="r:/builds/2018.3/continuous/2018_12_06_2405991/src/products/hls/hls_lib/hlsmath/include/FloatingPoint\hls_case_IEEE754.h" linenumber="20" name="tmp_13" contextFuncName="generic_cast_IEEE754&lt;int, 6, double&gt;" moduleName="snake_output" rtlName="tmp_13_fu_784_p1" latency="0" BRAM="-1" DSP="-1" FF="-1" LUT="-1" fileDirectory="r:\builds\2018.3\continuous\2018_12_06_2405991\src\products"><\/item>
<item  id="123" filename="r:/builds/2018.3/continuous/2018_12_06_2405991/src/products/hls/hls_lib/hlsmath/include/FloatingPoint\hls_case_IEEE754.h" linenumber="20" name="tmp_15" contextFuncName="generic_cast_IEEE754&lt;int, 6, double&gt;" moduleName="snake_output" rtlName="tmp_15_fu_788_p4" latency="0" BRAM="-1" DSP="-1" FF="-1" LUT="-1" fileDirectory="r:\builds\2018.3\continuous\2018_12_06_2405991\src\products"><\/item>
<item  id="124" filename="r:/builds/2018.3/continuous/2018_12_06_2405991/src/products/hls/hls_lib/hlsmath/include/FloatingPoint\hls_case_IEEE754.h" linenumber="17" name="p_Val2_18" contextFuncName="generic_cast_IEEE754&lt;int, 6, double&gt;" moduleName="snake_output" rtlName="p_Val2_18_fu_798_p3" latency="0" BRAM="-1" DSP="-1" FF="0" LUT="32" fileDirectory="r:\builds\2018.3\continuous\2018_12_06_2405991\src\products"><\/item>
<item  id="125" filename="r:/builds/2018.3/continuous/2018_12_06_2405991/src/products/hls/hls_lib/hlsmath/include/FloatingPoint\hls_case_IEEE754.h" linenumber="58" name="result_V_1" contextFuncName="generic_cast_IEEE754&lt;int, 6, double&gt;" moduleName="snake_output" rtlName="result_V_1_fu_806_p2" latency="0" BRAM="-1" DSP="-1" FF="0" LUT="39" fileDirectory="r:\builds\2018.3\continuous\2018_12_06_2405991\src\products"><\/item>
<item  id="126" filename="r:/builds/2018.3/continuous/2018_12_06_2405991/src/products/hls/hls_lib/hlsmath/include/FloatingPoint\hls_case_IEEE754.h" linenumber="58" name="p_Val2_19" contextFuncName="generic_cast_IEEE754&lt;int, 6, double&gt;" moduleName="snake_output" rtlName="p_Val2_19_fu_811_p3" latency="0" BRAM="-1" DSP="-1" FF="0" LUT="32" fileDirectory="r:\builds\2018.3\continuous\2018_12_06_2405991\src\products"><\/item>
<item  id="127" filename="src/snake_output.cpp" linenumber="33" name="tmp_s" contextFuncName="snake_output" moduleName="snake_output" rtlName="snake_output_sitofYi_U9" latency="5" BRAM="-1" DSP="-1" FF="-1" LUT="-1" fileDirectory="C:\Users\shinderink\REC\snake_output"><\/item>
<item  id="128" filename="src/snake_output.cpp" linenumber="33" name="f" contextFuncName="snake_output" moduleName="snake_output" rtlName="snake_output_dsubbkb_U1" latency="4" BRAM="-1" DSP="-1" FF="-1" LUT="-1" fileDirectory="C:\Users\shinderink\REC\snake_output"><\/item>
<item  id="129" filename="src/snake_output.cpp" linenumber="36" name="q" contextFuncName="snake_output" moduleName="snake_output" rtlName="snake_output_dsubbkb_U2" latency="4" BRAM="-1" DSP="-1" FF="-1" LUT="-1" fileDirectory="C:\Users\shinderink\REC\snake_output"><\/item>
<item  id="130" filename="src/snake_output.cpp" linenumber="37" name="t" contextFuncName="snake_output" moduleName="snake_output" rtlName="snake_output_dsubbkb_U3" latency="4" BRAM="-1" DSP="-1" FF="-1" LUT="-1" fileDirectory="C:\Users\shinderink\REC\snake_output"><\/item>
<item  id="131" filename="src/snake_output.cpp" linenumber="40" name="sel_tmp" contextFuncName="snake_output" moduleName="snake_output" rtlName="sel_tmp_fu_817_p2" latency="0" BRAM="-1" DSP="-1" FF="0" LUT="18" fileDirectory="C:\Users\shinderink\REC\snake_output"><\/item>
<item  id="132" filename="src/snake_output.cpp" linenumber="40" name="sel_tmp1" contextFuncName="snake_output" moduleName="snake_output" rtlName="sel_tmp1_fu_867_p3" latency="0" BRAM="-1" DSP="-1" FF="0" LUT="64" fileDirectory="C:\Users\shinderink\REC\snake_output"><\/item>
<item  id="133" filename="src/snake_output.cpp" linenumber="40" name="sel_tmp2" contextFuncName="snake_output" moduleName="snake_output" rtlName="sel_tmp2_fu_822_p2" latency="0" BRAM="-1" DSP="-1" FF="0" LUT="18" fileDirectory="C:\Users\shinderink\REC\snake_output"><\/item>
<item  id="134" filename="src/snake_output.cpp" linenumber="40" name="sel_tmp3" contextFuncName="snake_output" moduleName="snake_output" rtlName="sel_tmp3_fu_874_p3" latency="0" BRAM="-1" DSP="-1" FF="0" LUT="64" fileDirectory="C:\Users\shinderink\REC\snake_output"><\/item>
<item  id="135" filename="src/snake_output.cpp" linenumber="40" name="sel_tmp4" contextFuncName="snake_output" moduleName="snake_output" rtlName="sel_tmp4_fu_827_p2" latency="0" BRAM="-1" DSP="-1" FF="0" LUT="18" fileDirectory="C:\Users\shinderink\REC\snake_output"><\/item>
<item  id="136" filename="src/snake_output.cpp" linenumber="40" name="sel_tmp6" contextFuncName="snake_output" moduleName="snake_output" rtlName="sel_tmp6_fu_832_p2" latency="0" BRAM="-1" DSP="-1" FF="0" LUT="18" fileDirectory="C:\Users\shinderink\REC\snake_output"><\/item>
<item  id="137" filename="src/snake_output.cpp" linenumber="40" name="tmp_10" contextFuncName="snake_output" moduleName="snake_output" rtlName="tmp_10_fu_880_p2" latency="0" BRAM="-1" DSP="-1" FF="0" LUT="2" fileDirectory="C:\Users\shinderink\REC\snake_output"><\/item>
<item  id="138" filename="src/snake_output.cpp" linenumber="40" name="sel_tmp7" contextFuncName="snake_output" moduleName="snake_output" rtlName="sel_tmp7_fu_884_p3" latency="0" BRAM="-1" DSP="-1" FF="0" LUT="64" fileDirectory="C:\Users\shinderink\REC\snake_output"><\/item>
<item  id="139" filename="src/snake_output.cpp" linenumber="40" name="sel_tmp8" contextFuncName="snake_output" moduleName="snake_output" rtlName="sel_tmp8_fu_837_p2" latency="0" BRAM="-1" DSP="-1" FF="0" LUT="18" fileDirectory="C:\Users\shinderink\REC\snake_output"><\/item>
<item  id="140" filename="src/snake_output.cpp" linenumber="40" name="sel_tmp9" contextFuncName="snake_output" moduleName="snake_output" rtlName="sel_tmp9_fu_892_p3" latency="0" BRAM="-1" DSP="-1" FF="0" LUT="64" fileDirectory="C:\Users\shinderink\REC\snake_output"><\/item>
<item  id="141" filename="src/snake_output.cpp" linenumber="40" name="sel_tmp5" contextFuncName="snake_output" moduleName="snake_output" rtlName="sel_tmp5_fu_842_p2" latency="0" BRAM="-1" DSP="-1" FF="0" LUT="18" fileDirectory="C:\Users\shinderink\REC\snake_output"><\/item>
<item  id="142" filename="src/snake_output.cpp" linenumber="40" name="sel_tmp10" contextFuncName="snake_output" moduleName="snake_output" rtlName="sel_tmp10_fu_847_p2" latency="0" BRAM="-1" DSP="-1" FF="0" LUT="18" fileDirectory="C:\Users\shinderink\REC\snake_output"><\/item>
<item  id="143" filename="src/snake_output.cpp" linenumber="40" name="sel_tmp11" contextFuncName="snake_output" moduleName="snake_output" rtlName="sel_tmp11_fu_852_p2" latency="0" BRAM="-1" DSP="-1" FF="0" LUT="2" fileDirectory="C:\Users\shinderink\REC\snake_output"><\/item>
<item  id="144" filename="src/snake_output.cpp" linenumber="40" name="r_3" contextFuncName="snake_output" moduleName="snake_output" rtlName="r_3_fu_898_p3" latency="0" BRAM="-1" DSP="-1" FF="0" LUT="64" fileDirectory="C:\Users\shinderink\REC\snake_output"><\/item>
<item  id="145" filename="src/snake_output.cpp" linenumber="40" name="tmp_17" contextFuncName="snake_output" moduleName="snake_output" rtlName="tmp_17_fu_905_p2" latency="0" BRAM="-1" DSP="-1" FF="0" LUT="2" fileDirectory="C:\Users\shinderink\REC\snake_output"><\/item>
<item  id="146" filename="src/snake_output.cpp" linenumber="40" name="sel_tmp12" contextFuncName="snake_output" moduleName="snake_output" rtlName="sel_tmp12_fu_909_p3" latency="0" BRAM="-1" DSP="-1" FF="0" LUT="64" fileDirectory="C:\Users\shinderink\REC\snake_output"><\/item>
<item  id="147" filename="src/snake_output.cpp" linenumber="40" name="sel_tmp13" contextFuncName="snake_output" moduleName="snake_output" rtlName="sel_tmp13_fu_917_p3" latency="0" BRAM="-1" DSP="-1" FF="0" LUT="64" fileDirectory="C:\Users\shinderink\REC\snake_output"><\/item>
<item  id="148" filename="src/snake_output.cpp" linenumber="40" name="tmp_18" contextFuncName="snake_output" moduleName="snake_output" rtlName="tmp_18_fu_923_p2" latency="0" BRAM="-1" DSP="-1" FF="0" LUT="2" fileDirectory="C:\Users\shinderink\REC\snake_output"><\/item>
<item  id="149" filename="src/snake_output.cpp" linenumber="40" name="sel_tmp14" contextFuncName="snake_output" moduleName="snake_output" rtlName="sel_tmp14_fu_927_p3" latency="0" BRAM="-1" DSP="-1" FF="0" LUT="64" fileDirectory="C:\Users\shinderink\REC\snake_output"><\/item>
<item  id="150" filename="src/snake_output.cpp" linenumber="40" name="g_3" contextFuncName="snake_output" moduleName="snake_output" rtlName="g_3_fu_935_p3" latency="0" BRAM="-1" DSP="-1" FF="0" LUT="64" fileDirectory="C:\Users\shinderink\REC\snake_output"><\/item>
<item  id="151" filename="src/snake_output.cpp" linenumber="40" name="sel_tmp15" contextFuncName="snake_output" moduleName="snake_output" rtlName="sel_tmp15_fu_941_p3" latency="0" BRAM="-1" DSP="-1" FF="0" LUT="64" fileDirectory="C:\Users\shinderink\REC\snake_output"><\/item>
<item  id="152" filename="src/snake_output.cpp" linenumber="40" name="tmp_19" contextFuncName="snake_output" moduleName="snake_output" rtlName="tmp_19_fu_947_p2" latency="0" BRAM="-1" DSP="-1" FF="0" LUT="2" fileDirectory="C:\Users\shinderink\REC\snake_output"><\/item>
<item  id="153" filename="src/snake_output.cpp" linenumber="40" name="sel_tmp16" contextFuncName="snake_output" moduleName="snake_output" rtlName="sel_tmp16_fu_951_p3" latency="0" BRAM="-1" DSP="-1" FF="0" LUT="64" fileDirectory="C:\Users\shinderink\REC\snake_output"><\/item>
<item  id="154" filename="src/snake_output.cpp" linenumber="40" name="sel_tmp17" contextFuncName="snake_output" moduleName="snake_output" rtlName="sel_tmp17_fu_959_p3" latency="0" BRAM="-1" DSP="-1" FF="0" LUT="64" fileDirectory="C:\Users\shinderink\REC\snake_output"><\/item>
<item  id="155" filename="src/snake_output.cpp" linenumber="40" name="tmp_20" contextFuncName="snake_output" moduleName="snake_output" rtlName="tmp_20_fu_965_p2" latency="0" BRAM="-1" DSP="-1" FF="0" LUT="2" fileDirectory="C:\Users\shinderink\REC\snake_output"><\/item>
<item  id="156" filename="src/snake_output.cpp" linenumber="40" name="b_3" contextFuncName="snake_output" moduleName="snake_output" rtlName="b_3_fu_969_p3" latency="0" BRAM="-1" DSP="-1" FF="0" LUT="64" fileDirectory="C:\Users\shinderink\REC\snake_output"><\/item>
<item  id="157" filename="src/snake_output.cpp" linenumber="49" name="x_assign_1" contextFuncName="snake_output" moduleName="snake_output" rtlName="snake_output_dmulcud_U4" latency="5" BRAM="-1" DSP="-1" FF="-1" LUT="-1" fileDirectory="C:\Users\shinderink\REC\snake_output"><\/item>
<item  id="158" filename="r:/builds/2018.3/continuous/2018_12_06_2405991/src/products/hls/hls_lib/src/hls\utils/x_hls_utils.h" linenumber="475" name="p_Val2_s" contextFuncName="fp_struct" moduleName="snake_output" rtlName="p_Val2_s_fu_996_p1" latency="0" BRAM="-1" DSP="-1" FF="-1" LUT="-1" fileDirectory="r:\builds\2018.3\continuous\2018_12_06_2405991\src\products"><\/item>
<item  id="159" filename="r:/builds/2018.3/continuous/2018_12_06_2405991/src/products/hls/hls_lib/src/hls\utils/x_hls_utils.h" linenumber="475" name="p_Result_s" contextFuncName="fp_struct" moduleName="snake_output" rtlName="p_Result_s_reg_1728" latency="0" BRAM="-1" DSP="-1" FF="-1" LUT="-1" fileDirectory="r:\builds\2018.3\continuous\2018_12_06_2405991\src\products"><\/item>
<item  id="160" filename="r:/builds/2018.3/continuous/2018_12_06_2405991/src/products/hls/hls_lib/src/hls\utils/x_hls_utils.h" linenumber="477" name="tmp_V_2" contextFuncName="fp_struct" moduleName="snake_output" rtlName="tmp_V_2_fu_1007_p4" latency="0" BRAM="-1" DSP="-1" FF="-1" LUT="-1" fileDirectory="r:\builds\2018.3\continuous\2018_12_06_2405991\src\products"><\/item>
<item  id="161" filename="r:/builds/2018.3/continuous/2018_12_06_2405991/src/products/hls/hls_lib/src/hls\utils/x_hls_utils.h" linenumber="478" name="tmp_V_3" contextFuncName="fp_struct" moduleName="snake_output" rtlName="tmp_V_3_fu_1017_p1" latency="0" BRAM="-1" DSP="-1" FF="-1" LUT="-1" fileDirectory="r:\builds\2018.3\continuous\2018_12_06_2405991\src\products"><\/item>
<item  id="162" filename="r:/builds/2018.3/continuous/2018_12_06_2405991/src/products/hls/hls_lib/hlsmath/include/FloatingPoint\hls_case_IEEE754.h" linenumber="14" name="mantissa_V_1" contextFuncName="generic_cast_IEEE754&lt;int, 6, double&gt;" moduleName="snake_output" rtlName="mantissa_V_1_fu_1021_p4" latency="0" BRAM="-1" DSP="-1" FF="-1" LUT="-1" fileDirectory="r:\builds\2018.3\continuous\2018_12_06_2405991\src\products"><\/item>
<item  id="163" filename="r:/builds/2018.3/continuous/2018_12_06_2405991/src/products/hls/hls_lib/hlsmath/include/FloatingPoint\hls_case_IEEE754.h" linenumber="14" name="mantissa_V_3_cast" contextFuncName="generic_cast_IEEE754&lt;int, 6, double&gt;" moduleName="snake_output" rtlName="mantissa_V_3_cast_fu_1031_p1" latency="0" BRAM="-1" DSP="-1" FF="-1" LUT="-1" fileDirectory="r:\builds\2018.3\continuous\2018_12_06_2405991\src\products"><\/item>
<item  id="164" filename="r:/builds/2018.3/continuous/2018_12_06_2405991/src/products/hls/hls_lib/src/hls\utils/x_hls_utils.h" linenumber="502" name="tmp_i_i_i_i1_cast" contextFuncName="expv" moduleName="snake_output" rtlName="tmp_i_i_i_i1_cast_fu_1035_p1" latency="0" BRAM="-1" DSP="-1" FF="-1" LUT="-1" fileDirectory="r:\builds\2018.3\continuous\2018_12_06_2405991\src\products"><\/item>
<item  id="165" filename="r:/builds/2018.3/continuous/2018_12_06_2405991/src/products/hls/hls_lib/src/hls\utils/x_hls_utils.h" linenumber="502" name="sh_assign_3" contextFuncName="expv" moduleName="snake_output" rtlName="sh_assign_3_fu_1039_p2" latency="0" BRAM="-1" DSP="-1" FF="0" LUT="12" fileDirectory="r:\builds\2018.3\continuous\2018_12_06_2405991\src\products"><\/item>
<item  id="166" filename="r:/builds/2018.3/continuous/2018_12_06_2405991/src/products/hls/hls_lib/hlsmath/include/FloatingPoint\hls_case_IEEE754.h" linenumber="17" name="isNeg_1" contextFuncName="generic_cast_IEEE754&lt;int, 6, double&gt;" moduleName="snake_output" rtlName="isNeg_1_fu_1045_p3" latency="0" BRAM="-1" DSP="-1" FF="-1" LUT="-1" fileDirectory="r:\builds\2018.3\continuous\2018_12_06_2405991\src\products"><\/item>
<item  id="167" filename="r:/builds/2018.3/continuous/2018_12_06_2405991/src/products/hls/hls_lib/hlsmath/include/FloatingPoint\hls_case_IEEE754.h" linenumber="17" name="tmp_i_i_i1" contextFuncName="generic_cast_IEEE754&lt;int, 6, double&gt;" moduleName="snake_output" rtlName="tmp_i_i_i1_fu_1053_p2" latency="0" BRAM="-1" DSP="-1" FF="0" LUT="13" fileDirectory="r:\builds\2018.3\continuous\2018_12_06_2405991\src\products"><\/item>
<item  id="168" filename="r:/builds/2018.3/continuous/2018_12_06_2405991/src/products/hls/hls_lib/hlsmath/include/FloatingPoint\hls_case_IEEE754.h" linenumber="17" name="tmp_i_i_i1_cast" contextFuncName="generic_cast_IEEE754&lt;int, 6, double&gt;" moduleName="snake_output" rtlName="tmp_i_i_i1_cast_fu_1059_p1" latency="0" BRAM="-1" DSP="-1" FF="-1" LUT="-1" fileDirectory="r:\builds\2018.3\continuous\2018_12_06_2405991\src\products"><\/item>
<item  id="169" filename="r:/builds/2018.3/continuous/2018_12_06_2405991/src/products/hls/hls_lib/hlsmath/include/FloatingPoint\hls_case_IEEE754.h" linenumber="17" name="ush_1" contextFuncName="generic_cast_IEEE754&lt;int, 6, double&gt;" moduleName="snake_output" rtlName="ush_1_fu_1063_p3" latency="0" BRAM="-1" DSP="-1" FF="0" LUT="12" fileDirectory="r:\builds\2018.3\continuous\2018_12_06_2405991\src\products"><\/item>
<item  id="170" filename="r:/builds/2018.3/continuous/2018_12_06_2405991/src/products/hls/hls_lib/hlsmath/include/FloatingPoint\hls_case_IEEE754.h" linenumber="17" name="sh_assign_5_cast" contextFuncName="generic_cast_IEEE754&lt;int, 6, double&gt;" moduleName="snake_output" rtlName="sh_assign_5_cast_fu_1071_p1" latency="0" BRAM="-1" DSP="-1" FF="-1" LUT="-1" fileDirectory="r:\builds\2018.3\continuous\2018_12_06_2405991\src\products"><\/item>
<item  id="171" filename="r:/builds/2018.3/continuous/2018_12_06_2405991/src/products/hls/hls_lib/hlsmath/include/FloatingPoint\hls_case_IEEE754.h" linenumber="17" name="tmp_i_i_i1_11" contextFuncName="generic_cast_IEEE754&lt;int, 6, double&gt;" moduleName="snake_output" rtlName="tmp_i_i_i1_11_fu_1075_p1" latency="0" BRAM="-1" DSP="-1" FF="-1" LUT="-1" fileDirectory="r:\builds\2018.3\continuous\2018_12_06_2405991\src\products"><\/item>
<item  id="172" filename="r:/builds/2018.3/continuous/2018_12_06_2405991/src/products/hls/hls_lib/hlsmath/include/FloatingPoint\hls_case_IEEE754.h" linenumber="17" name="tmp_i_i_i1_cast_12" contextFuncName="generic_cast_IEEE754&lt;int, 6, double&gt;" moduleName="snake_output" rtlName="tmp_i_i_i1_cast_12_fu_1079_p1" latency="0" BRAM="-1" DSP="-1" FF="-1" LUT="-1" fileDirectory="r:\builds\2018.3\continuous\2018_12_06_2405991\src\products"><\/item>
<item  id="173" filename="r:/builds/2018.3/continuous/2018_12_06_2405991/src/products/hls/hls_lib/hlsmath/include/FloatingPoint\hls_case_IEEE754.h" linenumber="17" name="r_V_2" contextFuncName="generic_cast_IEEE754&lt;int, 6, double&gt;" moduleName="snake_output" rtlName="r_V_2_fu_1083_p2" latency="0" BRAM="-1" DSP="-1" FF="0" LUT="162" fileDirectory="r:\builds\2018.3\continuous\2018_12_06_2405991\src\products"><\/item>
<item  id="174" filename="r:/builds/2018.3/continuous/2018_12_06_2405991/src/products/hls/hls_lib/hlsmath/include/FloatingPoint\hls_case_IEEE754.h" linenumber="17" name="r_V_3" contextFuncName="generic_cast_IEEE754&lt;int, 6, double&gt;" moduleName="snake_output" rtlName="r_V_3_fu_1089_p2" latency="0" BRAM="-1" DSP="-1" FF="0" LUT="474" fileDirectory="r:\builds\2018.3\continuous\2018_12_06_2405991\src\products"><\/item>
<item  id="175" filename="r:/builds/2018.3/continuous/2018_12_06_2405991/src/products/hls/hls_lib/hlsmath/include/FloatingPoint\hls_case_IEEE754.h" linenumber="58" name="tmp_25" contextFuncName="generic_cast_IEEE754&lt;int, 6, double&gt;" moduleName="snake_output" rtlName="tmp_25_fu_1095_p3" latency="0" BRAM="-1" DSP="-1" FF="-1" LUT="-1" fileDirectory="r:\builds\2018.3\continuous\2018_12_06_2405991\src\products"><\/item>
<item  id="176" filename="r:/builds/2018.3/continuous/2018_12_06_2405991/src/products/hls/hls_lib/hlsmath/include/FloatingPoint\hls_case_IEEE754.h" linenumber="58" name="tmp_21" contextFuncName="generic_cast_IEEE754&lt;int, 6, double&gt;" moduleName="snake_output" rtlName="tmp_21_fu_1103_p1" latency="0" BRAM="-1" DSP="-1" FF="-1" LUT="-1" fileDirectory="r:\builds\2018.3\continuous\2018_12_06_2405991\src\products"><\/item>
<item  id="177" filename="r:/builds/2018.3/continuous/2018_12_06_2405991/src/products/hls/hls_lib/hlsmath/include/FloatingPoint\hls_case_IEEE754.h" linenumber="58" name="tmp_22" contextFuncName="generic_cast_IEEE754&lt;int, 6, double&gt;" moduleName="snake_output" rtlName="tmp_22_fu_1107_p4" latency="0" BRAM="-1" DSP="-1" FF="-1" LUT="-1" fileDirectory="r:\builds\2018.3\continuous\2018_12_06_2405991\src\products"><\/item>
<item  id="178" filename="r:/builds/2018.3/continuous/2018_12_06_2405991/src/products/hls/hls_lib/hlsmath/include/FloatingPoint\hls_case_IEEE754.h" linenumber="17" name="tmp_24" contextFuncName="generic_cast_IEEE754&lt;int, 6, double&gt;" moduleName="snake_output" rtlName="tmp_24_fu_1117_p3" latency="0" BRAM="-1" DSP="-1" FF="0" LUT="8" fileDirectory="r:\builds\2018.3\continuous\2018_12_06_2405991\src\products"><\/item>
<item  id="179" filename="r:/builds/2018.3/continuous/2018_12_06_2405991/src/products/hls/hls_lib/hlsmath/include/FloatingPoint\hls_case_IEEE754.h" linenumber="58" name="result_V_3" contextFuncName="generic_cast_IEEE754&lt;int, 6, double&gt;" moduleName="snake_output" rtlName="result_V_3_fu_1407_p2" latency="0" BRAM="-1" DSP="-1" FF="0" LUT="15" fileDirectory="r:\builds\2018.3\continuous\2018_12_06_2405991\src\products"><\/item>
<item  id="180" filename="r:/builds/2018.3/continuous/2018_12_06_2405991/src/products/hls/hls_lib/hlsmath/include/FloatingPoint\hls_case_IEEE754.h" linenumber="58" name="tmp_23" contextFuncName="generic_cast_IEEE754&lt;int, 6, double&gt;" moduleName="snake_output" rtlName="tmp_23_fu_1412_p3" latency="0" BRAM="-1" DSP="-1" FF="0" LUT="8" fileDirectory="r:\builds\2018.3\continuous\2018_12_06_2405991\src\products"><\/item>
<item  id="181" filename="src/snake_output.cpp" linenumber="50" name="x_assign_2" contextFuncName="snake_output" moduleName="snake_output" rtlName="snake_output_dmulcud_U5" latency="5" BRAM="-1" DSP="-1" FF="-1" LUT="-1" fileDirectory="C:\Users\shinderink\REC\snake_output"><\/item>
<item  id="182" filename="r:/builds/2018.3/continuous/2018_12_06_2405991/src/products/hls/hls_lib/src/hls\utils/x_hls_utils.h" linenumber="475" name="p_Val2_8" contextFuncName="fp_struct" moduleName="snake_output" rtlName="p_Val2_8_fu_1125_p1" latency="0" BRAM="-1" DSP="-1" FF="-1" LUT="-1" fileDirectory="r:\builds\2018.3\continuous\2018_12_06_2405991\src\products"><\/item>
<item  id="183" filename="r:/builds/2018.3/continuous/2018_12_06_2405991/src/products/hls/hls_lib/src/hls\utils/x_hls_utils.h" linenumber="475" name="p_Result_1" contextFuncName="fp_struct" moduleName="snake_output" rtlName="p_Result_1_reg_1739" latency="0" BRAM="-1" DSP="-1" FF="-1" LUT="-1" fileDirectory="r:\builds\2018.3\continuous\2018_12_06_2405991\src\products"><\/item>
<item  id="184" filename="r:/builds/2018.3/continuous/2018_12_06_2405991/src/products/hls/hls_lib/src/hls\utils/x_hls_utils.h" linenumber="477" name="tmp_V_4" contextFuncName="fp_struct" moduleName="snake_output" rtlName="tmp_V_4_fu_1136_p4" latency="0" BRAM="-1" DSP="-1" FF="-1" LUT="-1" fileDirectory="r:\builds\2018.3\continuous\2018_12_06_2405991\src\products"><\/item>
<item  id="185" filename="r:/builds/2018.3/continuous/2018_12_06_2405991/src/products/hls/hls_lib/src/hls\utils/x_hls_utils.h" linenumber="478" name="tmp_V_5" contextFuncName="fp_struct" moduleName="snake_output" rtlName="tmp_V_5_fu_1146_p1" latency="0" BRAM="-1" DSP="-1" FF="-1" LUT="-1" fileDirectory="r:\builds\2018.3\continuous\2018_12_06_2405991\src\products"><\/item>
<item  id="186" filename="r:/builds/2018.3/continuous/2018_12_06_2405991/src/products/hls/hls_lib/hlsmath/include/FloatingPoint\hls_case_IEEE754.h" linenumber="14" name="mantissa_V_2" contextFuncName="generic_cast_IEEE754&lt;int, 6, double&gt;" moduleName="snake_output" rtlName="mantissa_V_2_fu_1150_p4" latency="0" BRAM="-1" DSP="-1" FF="-1" LUT="-1" fileDirectory="r:\builds\2018.3\continuous\2018_12_06_2405991\src\products"><\/item>
<item  id="187" filename="r:/builds/2018.3/continuous/2018_12_06_2405991/src/products/hls/hls_lib/hlsmath/include/FloatingPoint\hls_case_IEEE754.h" linenumber="14" name="mantissa_V_5_cast" contextFuncName="generic_cast_IEEE754&lt;int, 6, double&gt;" moduleName="snake_output" rtlName="mantissa_V_5_cast_fu_1160_p1" latency="0" BRAM="-1" DSP="-1" FF="-1" LUT="-1" fileDirectory="r:\builds\2018.3\continuous\2018_12_06_2405991\src\products"><\/item>
<item  id="188" filename="r:/builds/2018.3/continuous/2018_12_06_2405991/src/products/hls/hls_lib/src/hls\utils/x_hls_utils.h" linenumber="502" name="tmp_i_i_i_i2_cast" contextFuncName="expv" moduleName="snake_output" rtlName="tmp_i_i_i_i2_cast_fu_1164_p1" latency="0" BRAM="-1" DSP="-1" FF="-1" LUT="-1" fileDirectory="r:\builds\2018.3\continuous\2018_12_06_2405991\src\products"><\/item>
<item  id="189" filename="r:/builds/2018.3/continuous/2018_12_06_2405991/src/products/hls/hls_lib/src/hls\utils/x_hls_utils.h" linenumber="502" name="sh_assign_6" contextFuncName="expv" moduleName="snake_output" rtlName="sh_assign_6_fu_1168_p2" latency="0" BRAM="-1" DSP="-1" FF="0" LUT="12" fileDirectory="r:\builds\2018.3\continuous\2018_12_06_2405991\src\products"><\/item>
<item  id="190" filename="r:/builds/2018.3/continuous/2018_12_06_2405991/src/products/hls/hls_lib/hlsmath/include/FloatingPoint\hls_case_IEEE754.h" linenumber="17" name="isNeg_2" contextFuncName="generic_cast_IEEE754&lt;int, 6, double&gt;" moduleName="snake_output" rtlName="isNeg_2_fu_1174_p3" latency="0" BRAM="-1" DSP="-1" FF="-1" LUT="-1" fileDirectory="r:\builds\2018.3\continuous\2018_12_06_2405991\src\products"><\/item>
<item  id="191" filename="r:/builds/2018.3/continuous/2018_12_06_2405991/src/products/hls/hls_lib/hlsmath/include/FloatingPoint\hls_case_IEEE754.h" linenumber="17" name="tmp_i_i_i2" contextFuncName="generic_cast_IEEE754&lt;int, 6, double&gt;" moduleName="snake_output" rtlName="tmp_i_i_i2_fu_1182_p2" latency="0" BRAM="-1" DSP="-1" FF="0" LUT="13" fileDirectory="r:\builds\2018.3\continuous\2018_12_06_2405991\src\products"><\/item>
<item  id="192" filename="r:/builds/2018.3/continuous/2018_12_06_2405991/src/products/hls/hls_lib/hlsmath/include/FloatingPoint\hls_case_IEEE754.h" linenumber="17" name="tmp_i_i_i2_cast" contextFuncName="generic_cast_IEEE754&lt;int, 6, double&gt;" moduleName="snake_output" rtlName="tmp_i_i_i2_cast_fu_1188_p1" latency="0" BRAM="-1" DSP="-1" FF="-1" LUT="-1" fileDirectory="r:\builds\2018.3\continuous\2018_12_06_2405991\src\products"><\/item>
<item  id="193" filename="r:/builds/2018.3/continuous/2018_12_06_2405991/src/products/hls/hls_lib/hlsmath/include/FloatingPoint\hls_case_IEEE754.h" linenumber="17" name="ush_2" contextFuncName="generic_cast_IEEE754&lt;int, 6, double&gt;" moduleName="snake_output" rtlName="ush_2_fu_1192_p3" latency="0" BRAM="-1" DSP="-1" FF="0" LUT="12" fileDirectory="r:\builds\2018.3\continuous\2018_12_06_2405991\src\products"><\/item>
<item  id="194" filename="r:/builds/2018.3/continuous/2018_12_06_2405991/src/products/hls/hls_lib/hlsmath/include/FloatingPoint\hls_case_IEEE754.h" linenumber="17" name="sh_assign_8_cast" contextFuncName="generic_cast_IEEE754&lt;int, 6, double&gt;" moduleName="snake_output" rtlName="sh_assign_8_cast_fu_1200_p1" latency="0" BRAM="-1" DSP="-1" FF="-1" LUT="-1" fileDirectory="r:\builds\2018.3\continuous\2018_12_06_2405991\src\products"><\/item>
<item  id="195" filename="r:/builds/2018.3/continuous/2018_12_06_2405991/src/products/hls/hls_lib/hlsmath/include/FloatingPoint\hls_case_IEEE754.h" linenumber="17" name="tmp_i_i_i2_13" contextFuncName="generic_cast_IEEE754&lt;int, 6, double&gt;" moduleName="snake_output" rtlName="tmp_i_i_i2_13_fu_1204_p1" latency="0" BRAM="-1" DSP="-1" FF="-1" LUT="-1" fileDirectory="r:\builds\2018.3\continuous\2018_12_06_2405991\src\products"><\/item>
<item  id="196" filename="r:/builds/2018.3/continuous/2018_12_06_2405991/src/products/hls/hls_lib/hlsmath/include/FloatingPoint\hls_case_IEEE754.h" linenumber="17" name="tmp_i_i_i2_cast_14" contextFuncName="generic_cast_IEEE754&lt;int, 6, double&gt;" moduleName="snake_output" rtlName="tmp_i_i_i2_cast_14_fu_1208_p1" latency="0" BRAM="-1" DSP="-1" FF="-1" LUT="-1" fileDirectory="r:\builds\2018.3\continuous\2018_12_06_2405991\src\products"><\/item>
<item  id="197" filename="r:/builds/2018.3/continuous/2018_12_06_2405991/src/products/hls/hls_lib/hlsmath/include/FloatingPoint\hls_case_IEEE754.h" linenumber="17" name="r_V_4" contextFuncName="generic_cast_IEEE754&lt;int, 6, double&gt;" moduleName="snake_output" rtlName="r_V_4_fu_1212_p2" latency="0" BRAM="-1" DSP="-1" FF="0" LUT="162" fileDirectory="r:\builds\2018.3\continuous\2018_12_06_2405991\src\products"><\/item>
<item  id="198" filename="r:/builds/2018.3/continuous/2018_12_06_2405991/src/products/hls/hls_lib/hlsmath/include/FloatingPoint\hls_case_IEEE754.h" linenumber="17" name="r_V_5" contextFuncName="generic_cast_IEEE754&lt;int, 6, double&gt;" moduleName="snake_output" rtlName="r_V_5_fu_1218_p2" latency="0" BRAM="-1" DSP="-1" FF="0" LUT="474" fileDirectory="r:\builds\2018.3\continuous\2018_12_06_2405991\src\products"><\/item>
<item  id="199" filename="r:/builds/2018.3/continuous/2018_12_06_2405991/src/products/hls/hls_lib/hlsmath/include/FloatingPoint\hls_case_IEEE754.h" linenumber="20" name="tmp_29" contextFuncName="generic_cast_IEEE754&lt;int, 6, double&gt;" moduleName="snake_output" rtlName="tmp_29_fu_1224_p3" latency="0" BRAM="-1" DSP="-1" FF="-1" LUT="-1" fileDirectory="r:\builds\2018.3\continuous\2018_12_06_2405991\src\products"><\/item>
<item  id="200" filename="r:/builds/2018.3/continuous/2018_12_06_2405991/src/products/hls/hls_lib/hlsmath/include/FloatingPoint\hls_case_IEEE754.h" linenumber="20" name="tmp_26" contextFuncName="generic_cast_IEEE754&lt;int, 6, double&gt;" moduleName="snake_output" rtlName="tmp_26_fu_1232_p1" latency="0" BRAM="-1" DSP="-1" FF="-1" LUT="-1" fileDirectory="r:\builds\2018.3\continuous\2018_12_06_2405991\src\products"><\/item>
<item  id="201" filename="r:/builds/2018.3/continuous/2018_12_06_2405991/src/products/hls/hls_lib/hlsmath/include/FloatingPoint\hls_case_IEEE754.h" linenumber="20" name="tmp_27" contextFuncName="generic_cast_IEEE754&lt;int, 6, double&gt;" moduleName="snake_output" rtlName="tmp_27_fu_1236_p4" latency="0" BRAM="-1" DSP="-1" FF="-1" LUT="-1" fileDirectory="r:\builds\2018.3\continuous\2018_12_06_2405991\src\products"><\/item>
<item  id="202" filename="r:/builds/2018.3/continuous/2018_12_06_2405991/src/products/hls/hls_lib/hlsmath/include/FloatingPoint\hls_case_IEEE754.h" linenumber="17" name="p_Val2_20" contextFuncName="generic_cast_IEEE754&lt;int, 6, double&gt;" moduleName="snake_output" rtlName="p_Val2_20_fu_1246_p3" latency="0" BRAM="-1" DSP="-1" FF="0" LUT="32" fileDirectory="r:\builds\2018.3\continuous\2018_12_06_2405991\src\products"><\/item>
<item  id="203" filename="r:/builds/2018.3/continuous/2018_12_06_2405991/src/products/hls/hls_lib/hlsmath/include/FloatingPoint\hls_case_IEEE754.h" linenumber="58" name="result_V_4" contextFuncName="generic_cast_IEEE754&lt;int, 6, double&gt;" moduleName="snake_output" rtlName="result_V_4_fu_1419_p2" latency="0" BRAM="-1" DSP="-1" FF="0" LUT="39" fileDirectory="r:\builds\2018.3\continuous\2018_12_06_2405991\src\products"><\/item>
<item  id="204" filename="r:/builds/2018.3/continuous/2018_12_06_2405991/src/products/hls/hls_lib/hlsmath/include/FloatingPoint\hls_case_IEEE754.h" linenumber="58" name="p_Val2_21" contextFuncName="generic_cast_IEEE754&lt;int, 6, double&gt;" moduleName="snake_output" rtlName="p_Val2_21_fu_1424_p3" latency="0" BRAM="-1" DSP="-1" FF="0" LUT="32" fileDirectory="r:\builds\2018.3\continuous\2018_12_06_2405991\src\products"><\/item>
<item  id="205" filename="src/snake_output.cpp" linenumber="51" name="x_assign_3" contextFuncName="snake_output" moduleName="snake_output" rtlName="snake_output_dmulcud_U6" latency="5" BRAM="-1" DSP="-1" FF="-1" LUT="-1" fileDirectory="C:\Users\shinderink\REC\snake_output"><\/item>
<item  id="206" filename="r:/builds/2018.3/continuous/2018_12_06_2405991/src/products/hls/hls_lib/src/hls\utils/x_hls_utils.h" linenumber="475" name="p_Val2_13" contextFuncName="fp_struct" moduleName="snake_output" rtlName="p_Val2_13_fu_1254_p1" latency="0" BRAM="-1" DSP="-1" FF="-1" LUT="-1" fileDirectory="r:\builds\2018.3\continuous\2018_12_06_2405991\src\products"><\/item>
<item  id="207" filename="r:/builds/2018.3/continuous/2018_12_06_2405991/src/products/hls/hls_lib/src/hls\utils/x_hls_utils.h" linenumber="475" name="p_Result_2" contextFuncName="fp_struct" moduleName="snake_output" rtlName="p_Result_2_reg_1750" latency="0" BRAM="-1" DSP="-1" FF="-1" LUT="-1" fileDirectory="r:\builds\2018.3\continuous\2018_12_06_2405991\src\products"><\/item>
<item  id="208" filename="r:/builds/2018.3/continuous/2018_12_06_2405991/src/products/hls/hls_lib/src/hls\utils/x_hls_utils.h" linenumber="477" name="tmp_V_6" contextFuncName="fp_struct" moduleName="snake_output" rtlName="tmp_V_6_fu_1265_p4" latency="0" BRAM="-1" DSP="-1" FF="-1" LUT="-1" fileDirectory="r:\builds\2018.3\continuous\2018_12_06_2405991\src\products"><\/item>
<item  id="209" filename="r:/builds/2018.3/continuous/2018_12_06_2405991/src/products/hls/hls_lib/src/hls\utils/x_hls_utils.h" linenumber="478" name="tmp_V_7" contextFuncName="fp_struct" moduleName="snake_output" rtlName="tmp_V_7_fu_1275_p1" latency="0" BRAM="-1" DSP="-1" FF="-1" LUT="-1" fileDirectory="r:\builds\2018.3\continuous\2018_12_06_2405991\src\products"><\/item>
<item  id="210" filename="r:/builds/2018.3/continuous/2018_12_06_2405991/src/products/hls/hls_lib/hlsmath/include/FloatingPoint\hls_case_IEEE754.h" linenumber="14" name="mantissa_V_3" contextFuncName="generic_cast_IEEE754&lt;int, 6, double&gt;" moduleName="snake_output" rtlName="mantissa_V_3_fu_1279_p4" latency="0" BRAM="-1" DSP="-1" FF="-1" LUT="-1" fileDirectory="r:\builds\2018.3\continuous\2018_12_06_2405991\src\products"><\/item>
<item  id="211" filename="r:/builds/2018.3/continuous/2018_12_06_2405991/src/products/hls/hls_lib/hlsmath/include/FloatingPoint\hls_case_IEEE754.h" linenumber="14" name="mantissa_V_7_cast" contextFuncName="generic_cast_IEEE754&lt;int, 6, double&gt;" moduleName="snake_output" rtlName="mantissa_V_7_cast_fu_1289_p1" latency="0" BRAM="-1" DSP="-1" FF="-1" LUT="-1" fileDirectory="r:\builds\2018.3\continuous\2018_12_06_2405991\src\products"><\/item>
<item  id="212" filename="r:/builds/2018.3/continuous/2018_12_06_2405991/src/products/hls/hls_lib/src/hls\utils/x_hls_utils.h" linenumber="502" name="tmp_i_i_i_i3_cast" contextFuncName="expv" moduleName="snake_output" rtlName="tmp_i_i_i_i3_cast_fu_1293_p1" latency="0" BRAM="-1" DSP="-1" FF="-1" LUT="-1" fileDirectory="r:\builds\2018.3\continuous\2018_12_06_2405991\src\products"><\/item>
<item  id="213" filename="r:/builds/2018.3/continuous/2018_12_06_2405991/src/products/hls/hls_lib/src/hls\utils/x_hls_utils.h" linenumber="502" name="sh_assign_9" contextFuncName="expv" moduleName="snake_output" rtlName="sh_assign_9_fu_1297_p2" latency="0" BRAM="-1" DSP="-1" FF="0" LUT="12" fileDirectory="r:\builds\2018.3\continuous\2018_12_06_2405991\src\products"><\/item>
<item  id="214" filename="r:/builds/2018.3/continuous/2018_12_06_2405991/src/products/hls/hls_lib/hlsmath/include/FloatingPoint\hls_case_IEEE754.h" linenumber="17" name="isNeg_3" contextFuncName="generic_cast_IEEE754&lt;int, 6, double&gt;" moduleName="snake_output" rtlName="isNeg_3_fu_1303_p3" latency="0" BRAM="-1" DSP="-1" FF="-1" LUT="-1" fileDirectory="r:\builds\2018.3\continuous\2018_12_06_2405991\src\products"><\/item>
<item  id="215" filename="r:/builds/2018.3/continuous/2018_12_06_2405991/src/products/hls/hls_lib/hlsmath/include/FloatingPoint\hls_case_IEEE754.h" linenumber="17" name="tmp_i_i_i3" contextFuncName="generic_cast_IEEE754&lt;int, 6, double&gt;" moduleName="snake_output" rtlName="tmp_i_i_i3_fu_1311_p2" latency="0" BRAM="-1" DSP="-1" FF="0" LUT="13" fileDirectory="r:\builds\2018.3\continuous\2018_12_06_2405991\src\products"><\/item>
<item  id="216" filename="r:/builds/2018.3/continuous/2018_12_06_2405991/src/products/hls/hls_lib/hlsmath/include/FloatingPoint\hls_case_IEEE754.h" linenumber="17" name="tmp_i_i_i3_cast" contextFuncName="generic_cast_IEEE754&lt;int, 6, double&gt;" moduleName="snake_output" rtlName="tmp_i_i_i3_cast_fu_1317_p1" latency="0" BRAM="-1" DSP="-1" FF="-1" LUT="-1" fileDirectory="r:\builds\2018.3\continuous\2018_12_06_2405991\src\products"><\/item>
<item  id="217" filename="r:/builds/2018.3/continuous/2018_12_06_2405991/src/products/hls/hls_lib/hlsmath/include/FloatingPoint\hls_case_IEEE754.h" linenumber="17" name="ush_3" contextFuncName="generic_cast_IEEE754&lt;int, 6, double&gt;" moduleName="snake_output" rtlName="ush_3_fu_1321_p3" latency="0" BRAM="-1" DSP="-1" FF="0" LUT="12" fileDirectory="r:\builds\2018.3\continuous\2018_12_06_2405991\src\products"><\/item>
<item  id="218" filename="r:/builds/2018.3/continuous/2018_12_06_2405991/src/products/hls/hls_lib/hlsmath/include/FloatingPoint\hls_case_IEEE754.h" linenumber="17" name="sh_assign_11_cast" contextFuncName="generic_cast_IEEE754&lt;int, 6, double&gt;" moduleName="snake_output" rtlName="sh_assign_11_cast_fu_1329_p1" latency="0" BRAM="-1" DSP="-1" FF="-1" LUT="-1" fileDirectory="r:\builds\2018.3\continuous\2018_12_06_2405991\src\products"><\/item>
<item  id="219" filename="r:/builds/2018.3/continuous/2018_12_06_2405991/src/products/hls/hls_lib/hlsmath/include/FloatingPoint\hls_case_IEEE754.h" linenumber="17" name="tmp_i_i_i3_15" contextFuncName="generic_cast_IEEE754&lt;int, 6, double&gt;" moduleName="snake_output" rtlName="tmp_i_i_i3_15_fu_1333_p1" latency="0" BRAM="-1" DSP="-1" FF="-1" LUT="-1" fileDirectory="r:\builds\2018.3\continuous\2018_12_06_2405991\src\products"><\/item>
<item  id="220" filename="r:/builds/2018.3/continuous/2018_12_06_2405991/src/products/hls/hls_lib/hlsmath/include/FloatingPoint\hls_case_IEEE754.h" linenumber="17" name="tmp_i_i_i3_cast_16" contextFuncName="generic_cast_IEEE754&lt;int, 6, double&gt;" moduleName="snake_output" rtlName="tmp_i_i_i3_cast_16_fu_1337_p1" latency="0" BRAM="-1" DSP="-1" FF="-1" LUT="-1" fileDirectory="r:\builds\2018.3\continuous\2018_12_06_2405991\src\products"><\/item>
<item  id="221" filename="r:/builds/2018.3/continuous/2018_12_06_2405991/src/products/hls/hls_lib/hlsmath/include/FloatingPoint\hls_case_IEEE754.h" linenumber="17" name="r_V_6" contextFuncName="generic_cast_IEEE754&lt;int, 6, double&gt;" moduleName="snake_output" rtlName="r_V_6_fu_1341_p2" latency="0" BRAM="-1" DSP="-1" FF="0" LUT="162" fileDirectory="r:\builds\2018.3\continuous\2018_12_06_2405991\src\products"><\/item>
<item  id="222" filename="r:/builds/2018.3/continuous/2018_12_06_2405991/src/products/hls/hls_lib/hlsmath/include/FloatingPoint\hls_case_IEEE754.h" linenumber="17" name="r_V_7" contextFuncName="generic_cast_IEEE754&lt;int, 6, double&gt;" moduleName="snake_output" rtlName="r_V_7_fu_1347_p2" latency="0" BRAM="-1" DSP="-1" FF="0" LUT="474" fileDirectory="r:\builds\2018.3\continuous\2018_12_06_2405991\src\products"><\/item>
<item  id="223" filename="r:/builds/2018.3/continuous/2018_12_06_2405991/src/products/hls/hls_lib/hlsmath/include/FloatingPoint\hls_case_IEEE754.h" linenumber="20" name="tmp_33" contextFuncName="generic_cast_IEEE754&lt;int, 6, double&gt;" moduleName="snake_output" rtlName="tmp_33_fu_1353_p3" latency="0" BRAM="-1" DSP="-1" FF="-1" LUT="-1" fileDirectory="r:\builds\2018.3\continuous\2018_12_06_2405991\src\products"><\/item>
<item  id="224" filename="r:/builds/2018.3/continuous/2018_12_06_2405991/src/products/hls/hls_lib/hlsmath/include/FloatingPoint\hls_case_IEEE754.h" linenumber="20" name="tmp_28" contextFuncName="generic_cast_IEEE754&lt;int, 6, double&gt;" moduleName="snake_output" rtlName="tmp_28_fu_1361_p1" latency="0" BRAM="-1" DSP="-1" FF="-1" LUT="-1" fileDirectory="r:\builds\2018.3\continuous\2018_12_06_2405991\src\products"><\/item>
<item  id="225" filename="r:/builds/2018.3/continuous/2018_12_06_2405991/src/products/hls/hls_lib/hlsmath/include/FloatingPoint\hls_case_IEEE754.h" linenumber="20" name="tmp_30" contextFuncName="generic_cast_IEEE754&lt;int, 6, double&gt;" moduleName="snake_output" rtlName="tmp_30_fu_1365_p4" latency="0" BRAM="-1" DSP="-1" FF="-1" LUT="-1" fileDirectory="r:\builds\2018.3\continuous\2018_12_06_2405991\src\products"><\/item>
<item  id="226" filename="r:/builds/2018.3/continuous/2018_12_06_2405991/src/products/hls/hls_lib/hlsmath/include/FloatingPoint\hls_case_IEEE754.h" linenumber="17" name="p_Val2_22" contextFuncName="generic_cast_IEEE754&lt;int, 6, double&gt;" moduleName="snake_output" rtlName="p_Val2_22_fu_1375_p3" latency="0" BRAM="-1" DSP="-1" FF="0" LUT="32" fileDirectory="r:\builds\2018.3\continuous\2018_12_06_2405991\src\products"><\/item>
<item  id="227" filename="r:/builds/2018.3/continuous/2018_12_06_2405991/src/products/hls/hls_lib/hlsmath/include/FloatingPoint\hls_case_IEEE754.h" linenumber="58" name="result_V_6" contextFuncName="generic_cast_IEEE754&lt;int, 6, double&gt;" moduleName="snake_output" rtlName="result_V_6_fu_1431_p2" latency="0" BRAM="-1" DSP="-1" FF="0" LUT="39" fileDirectory="r:\builds\2018.3\continuous\2018_12_06_2405991\src\products"><\/item>
<item  id="228" filename="r:/builds/2018.3/continuous/2018_12_06_2405991/src/products/hls/hls_lib/hlsmath/include/FloatingPoint\hls_case_IEEE754.h" linenumber="58" name="p_Val2_23" contextFuncName="generic_cast_IEEE754&lt;int, 6, double&gt;" moduleName="snake_output" rtlName="p_Val2_23_fu_1436_p3" latency="0" BRAM="-1" DSP="-1" FF="0" LUT="32" fileDirectory="r:\builds\2018.3\continuous\2018_12_06_2405991\src\products"><\/item>
<item  id="237" filename="src/snake_output.cpp" linenumber="75" name="pixel_G" contextFuncName="snake_output" moduleName="snake_output" rtlName="pixel_G_fu_1443_p1" latency="0" BRAM="-1" DSP="-1" FF="-1" LUT="-1" fileDirectory="C:\Users\shinderink\REC\snake_output"><\/item>
<item  id="238" filename="r:/builds/2018.3/continuous/2018_12_06_2405991/src/products/hls/hls_lib/hlsmath/include/FloatingPoint\hls_case_IEEE754.h" linenumber="58" name="tmp_37" contextFuncName="generic_cast_IEEE754&lt;int, 6, double&gt;" moduleName="snake_output" rtlName="tmp_37_fu_1447_p1" latency="0" BRAM="-1" DSP="-1" FF="-1" LUT="-1" fileDirectory="r:\builds\2018.3\continuous\2018_12_06_2405991\src\products"><\/item>
<item  id="239" filename="src/snake_output.cpp" linenumber="92" name="tmp_data_V" contextFuncName="set_rgb_8_pixel_value" moduleName="snake_output" rtlName="tmp_data_V_fu_1451_p4" latency="0" BRAM="-1" DSP="-1" FF="-1" LUT="-1" fileDirectory="C:\Users\shinderink\REC\snake_output"><\/item>
<item  id="242" filename="src/snake_output.cpp" linenumber="16" name="col_V" contextFuncName="snake_output" moduleName="snake_output" rtlName="col_V_fu_569_p2" latency="0" BRAM="-1" DSP="-1" FF="0" LUT="14" fileDirectory="C:\Users\shinderink\REC\snake_output"><\/item>
<\/annotationInfo>
</annotationInfo>
